Metadata-Version: 2.1
Name: django_simple_file_handler
Version: 0.3.5
Summary: A Django app for storing and processing documents and images
Home-page: https://github.com/jonathanrickard/django-simple-file-handler
Author: Jonathan Rickard
Author-email: jonathan@jonathanrickard.com
License: MIT License
Keywords: django,files,images
Classifier: Environment :: Web Environment
Classifier: Framework :: Django
Classifier: Framework :: Django :: 4.2
Classifier: Framework :: Django :: 5.0
Classifier: Operating System :: OS Independent
Classifier: Programming Language :: Python
Classifier: Programming Language :: Python :: 3
Classifier: Programming Language :: Python :: 3.9
Classifier: Programming Language :: Python :: 3.10
Classifier: Programming Language :: Python :: 3.11
Classifier: Programming Language :: Python :: 3.12
Classifier: Intended Audience :: Developers
Classifier: Topic :: Internet :: WWW/HTTP
Classifier: License :: OSI Approved :: MIT License
License-File: LICENSE
Requires-Dist: Django <5.1,>=4.2
Requires-Dist: Pillow >=8.3.0
Requires-Dist: xhtml2pdf >=0.2.5
